{
  "id": "ConnectApi.actionlinks",
  "nodeType": "class",
  "name": "ActionLinks",
  "namespace": "ConnectApi",
  "startToken": {
    "type": "declaration.entity.name.class",
    "text": "ActionLinks",
    "textToLower": "actionlinks",
    "isAux": false,
    "range": {
      "start": {
        "line": -1,
        "character": 0
      },
      "end": {
        "line": -1,
        "character": 0
      },
      "isEmpty": true,
      "isSingleLine": true
    },
    "id": "declaration.entity.name.class_ActionLinks_-1:0"
  },
  "accessModifier": {
    "type": "keyword.modifier.access",
    "text": "global",
    "textToLower": "global",
    "isAux": false,
    "range": {
      "start": {
        "line": -1,
        "character": 0
      },
      "end": {
        "line": -1,
        "character": 0
      },
      "isEmpty": true,
      "isSingleLine": true
    },
    "id": "keyword.modifier.access_global_-1:0"
  },
  "sharingModifier": {
    "type": "keyword.modifier.sharing",
    "text": "without sharing",
    "textToLower": "without sharing",
    "isAux": false,
    "range": {
      "start": {
        "line": -1,
        "character": 0
      },
      "end": {
        "line": -1,
        "character": 0
      },
      "isEmpty": true,
      "isSingleLine": true
    },
    "id": "keyword.modifier.sharing_without sharing_-1:0"
  },
  "description": "Create, delete, and get information about an action link group definition; get information about an action link group; get action link diagnostic information.",
  "documentation": "https://developer.salesforce.com/docs/atlas.en-us.apexcode.meta/apexcode/apex_ConnectAPI_ActionLinks_static_methods.htm",
  "classes": {},
  "interfaces": {},
  "enums": {},
  "variables": {},
  "methods": {
    "createactionlinkgroupdefinition​(string,connectapi.actionlinkgroupdefinitioninput)": {
      "id": "ConnectApi.actionlinks.createactionlinkgroupdefinition​",
      "nodeType": "method",
      "name": "createActionLinkGroupDefinition​",
      "startToken": {
        "type": "declaration.entity.name.function",
        "text": "createActionLinkGroupDefinition​",
        "textToLower": "createactionlinkgroupdefinition​",
        "isAux": false,
        "range": {
          "start": {
            "line": -1,
            "character": 0
          },
          "end": {
            "line": -1,
            "character": 0
          },
          "isEmpty": true,
          "isSingleLine": true
        },
        "id": "declaration.entity.name.function_createActionLinkGroupDefinition​_-1:0"
      },
      "accessModifier": {
        "type": "keyword.modifier.access",
        "text": "public",
        "textToLower": "public",
        "isAux": false,
        "range": {
          "start": {
            "line": -1,
            "character": 0
          },
          "end": {
            "line": -1,
            "character": 0
          },
          "isEmpty": true,
          "isSingleLine": true
        },
        "id": "keyword.modifier.access_public_-1:0"
      },
      "static": {
        "type": "keyword.modifier.static",
        "text": "static",
        "textToLower": "static",
        "isAux": false,
        "range": {
          "start": {
            "line": -1,
            "character": 0
          },
          "end": {
            "line": -1,
            "character": 0
          },
          "isEmpty": true,
          "isSingleLine": true
        },
        "id": "keyword.modifier.static_static_-1:0"
      },
      "signature": "public static ConnectApi.ActionLinkGroupDefinition createActionLinkGroupDefinition​(String communityId, ConnectApi.ActionLinkGroupDefinitionInput actionLinkGroup)",
      "simplifiedSignature": "createActionLinkGroupDefinition​(String,ConnectApi.ActionLinkGroupDefinitionInput)",
      "datatype": {
        "id": "ConnectApi.actionlinks.createactionlinkgroupdefinition​.ConnectApi.ActionLinkGroupDefinition",
        "nodeType": "datatype",
        "name": "ConnectApi.ActionLinkGroupDefinition"
      },
      "description": "Create an action link group definition. To associate an action link group with a feed element, first create an action link group definition. Then post a feed element with an associated actions capability.",
      "params": {
        "communityId": {
          "id": "ConnectApi.actionlinks.createactionlinkgroupdefinition​.communityid",
          "type": "var",
          "name": "communityId",
          "startToken": {
            "type": "declaration.entity.name.variable",
            "text": "communityId",
            "textToLower": "communityid",
            "isAux": false,
            "range": {
              "start": {
                "line": -1,
                "character": 0
              },
              "end": {
                "line": -1,
                "character": 0
              },
              "isEmpty": true,
              "isSingleLine": true
            },
            "id": "declaration.entity.name.variable_communityId_-1:0"
          },
          "signature": "String communityId",
          "datatype": {
            "id": "ConnectApi.actionlinks.createactionlinkgroupdefinition​.string",
            "nodeType": "datatype",
            "name": "String"
          }
        },
        "actionLinkGroup": {
          "id": "ConnectApi.actionlinks.createactionlinkgroupdefinition​.actionlinkgroup",
          "type": "var",
          "name": "actionLinkGroup",
          "startToken": {
            "type": "declaration.entity.name.variable",
            "text": "actionLinkGroup",
            "textToLower": "actionlinkgroup",
            "isAux": false,
            "range": {
              "start": {
                "line": -1,
                "character": 0
              },
              "end": {
                "line": -1,
                "character": 0
              },
              "isEmpty": true,
              "isSingleLine": true
            },
            "id": "declaration.entity.name.variable_actionLinkGroup_-1:0"
          },
          "signature": "ConnectApi.ActionLinkGroupDefinitionInput actionLinkGroup",
          "datatype": {
            "id": "ConnectApi.actionlinks.createactionlinkgroupdefinition​.connectapi.actionlinkgroupdefinitioninput",
            "nodeType": "datatype",
            "name": "ConnectApi.ActionLinkGroupDefinitionInput"
          }
        }
      }
    },
    "deleteactionlinkgroupdefinition(string,string)": {
      "id": "ConnectApi.actionlinks.deleteactionlinkgroupdefinition",
      "nodeType": "method",
      "name": "deleteActionLinkGroupDefinition",
      "startToken": {
        "type": "declaration.entity.name.function",
        "text": "deleteActionLinkGroupDefinition",
        "textToLower": "deleteactionlinkgroupdefinition",
        "isAux": false,
        "range": {
          "start": {
            "line": -1,
            "character": 0
          },
          "end": {
            "line": -1,
            "character": 0
          },
          "isEmpty": true,
          "isSingleLine": true
        },
        "id": "declaration.entity.name.function_deleteActionLinkGroupDefinition_-1:0"
      },
      "accessModifier": {
        "type": "keyword.modifier.access",
        "text": "public",
        "textToLower": "public",
        "isAux": false,
        "range": {
          "start": {
            "line": -1,
            "character": 0
          },
          "end": {
            "line": -1,
            "character": 0
          },
          "isEmpty": true,
          "isSingleLine": true
        },
        "id": "keyword.modifier.access_public_-1:0"
      },
      "static": {
        "type": "keyword.modifier.static",
        "text": "static",
        "textToLower": "static",
        "isAux": false,
        "range": {
          "start": {
            "line": -1,
            "character": 0
          },
          "end": {
            "line": -1,
            "character": 0
          },
          "isEmpty": true,
          "isSingleLine": true
        },
        "id": "keyword.modifier.static_static_-1:0"
      },
      "signature": "public static void deleteActionLinkGroupDefinition(String communityId, String actionLinkGroupId)",
      "simplifiedSignature": "deleteActionLinkGroupDefinition(String,String)",
      "datatype": {
        "id": "ConnectApi.actionlinks.deleteactionlinkgroupdefinition.void",
        "nodeType": "datatype",
        "name": "void"
      },
      "description": "Delete an action link group definition. Deleting an action link group definition removes all references to it from feed elements.",
      "params": {
        "communityId": {
          "id": "ConnectApi.actionlinks.deleteactionlinkgroupdefinition.communityid",
          "type": "var",
          "name": "communityId",
          "startToken": {
            "type": "declaration.entity.name.variable",
            "text": "communityId",
            "textToLower": "communityid",
            "isAux": false,
            "range": {
              "start": {
                "line": -1,
                "character": 0
              },
              "end": {
                "line": -1,
                "character": 0
              },
              "isEmpty": true,
              "isSingleLine": true
            },
            "id": "declaration.entity.name.variable_communityId_-1:0"
          },
          "signature": "String communityId",
          "datatype": {
            "id": "ConnectApi.actionlinks.deleteactionlinkgroupdefinition.string",
            "nodeType": "datatype",
            "name": "String"
          }
        },
        "actionLinkGroupId": {
          "id": "ConnectApi.actionlinks.deleteactionlinkgroupdefinition.actionlinkgroupid",
          "type": "var",
          "name": "actionLinkGroupId",
          "startToken": {
            "type": "declaration.entity.name.variable",
            "text": "actionLinkGroupId",
            "textToLower": "actionlinkgroupid",
            "isAux": false,
            "range": {
              "start": {
                "line": -1,
                "character": 0
              },
              "end": {
                "line": -1,
                "character": 0
              },
              "isEmpty": true,
              "isSingleLine": true
            },
            "id": "declaration.entity.name.variable_actionLinkGroupId_-1:0"
          },
          "signature": "String actionLinkGroupId",
          "datatype": {
            "id": "ConnectApi.actionlinks.deleteactionlinkgroupdefinition.string",
            "nodeType": "datatype",
            "name": "String"
          }
        }
      }
    },
    "getactionlink(string,string)": {
      "id": "ConnectApi.actionlinks.getactionlink",
      "nodeType": "method",
      "name": "getActionLink",
      "startToken": {
        "type": "declaration.entity.name.function",
        "text": "getActionLink",
        "textToLower": "getactionlink",
        "isAux": false,
        "range": {
          "start": {
            "line": -1,
            "character": 0
          },
          "end": {
            "line": -1,
            "character": 0
          },
          "isEmpty": true,
          "isSingleLine": true
        },
        "id": "declaration.entity.name.function_getActionLink_-1:0"
      },
      "accessModifier": {
        "type": "keyword.modifier.access",
        "text": "public",
        "textToLower": "public",
        "isAux": false,
        "range": {
          "start": {
            "line": -1,
            "character": 0
          },
          "end": {
            "line": -1,
            "character": 0
          },
          "isEmpty": true,
          "isSingleLine": true
        },
        "id": "keyword.modifier.access_public_-1:0"
      },
      "static": {
        "type": "keyword.modifier.static",
        "text": "static",
        "textToLower": "static",
        "isAux": false,
        "range": {
          "start": {
            "line": -1,
            "character": 0
          },
          "end": {
            "line": -1,
            "character": 0
          },
          "isEmpty": true,
          "isSingleLine": true
        },
        "id": "keyword.modifier.static_static_-1:0"
      },
      "signature": "public static ConnectApi.PlatformAction getActionLink(String communityId, String actionLinkId)",
      "simplifiedSignature": "getActionLink(String,String)",
      "datatype": {
        "id": "ConnectApi.actionlinks.getactionlink.ConnectApi.PlatformAction",
        "nodeType": "datatype",
        "name": "ConnectApi.PlatformAction"
      },
      "description": "Get information about an action link, including state for the context user.",
      "params": {
        "communityId": {
          "id": "ConnectApi.actionlinks.getactionlink.communityid",
          "type": "var",
          "name": "communityId",
          "startToken": {
            "type": "declaration.entity.name.variable",
            "text": "communityId",
            "textToLower": "communityid",
            "isAux": false,
            "range": {
              "start": {
                "line": -1,
                "character": 0
              },
              "end": {
                "line": -1,
                "character": 0
              },
              "isEmpty": true,
              "isSingleLine": true
            },
            "id": "declaration.entity.name.variable_communityId_-1:0"
          },
          "signature": "String communityId",
          "datatype": {
            "id": "ConnectApi.actionlinks.getactionlink.string",
            "nodeType": "datatype",
            "name": "String"
          }
        },
        "actionLinkId": {
          "id": "ConnectApi.actionlinks.getactionlink.actionlinkid",
          "type": "var",
          "name": "actionLinkId",
          "startToken": {
            "type": "declaration.entity.name.variable",
            "text": "actionLinkId",
            "textToLower": "actionlinkid",
            "isAux": false,
            "range": {
              "start": {
                "line": -1,
                "character": 0
              },
              "end": {
                "line": -1,
                "character": 0
              },
              "isEmpty": true,
              "isSingleLine": true
            },
            "id": "declaration.entity.name.variable_actionLinkId_-1:0"
          },
          "signature": "String actionLinkId",
          "datatype": {
            "id": "ConnectApi.actionlinks.getactionlink.string",
            "nodeType": "datatype",
            "name": "String"
          }
        }
      }
    },
    "getactionlinkdiagnosticinfo(string,string)": {
      "id": "ConnectApi.actionlinks.getactionlinkdiagnosticinfo",
      "nodeType": "method",
      "name": "getActionLinkDiagnosticInfo",
      "startToken": {
        "type": "declaration.entity.name.function",
        "text": "getActionLinkDiagnosticInfo",
        "textToLower": "getactionlinkdiagnosticinfo",
        "isAux": false,
        "range": {
          "start": {
            "line": -1,
            "character": 0
          },
          "end": {
            "line": -1,
            "character": 0
          },
          "isEmpty": true,
          "isSingleLine": true
        },
        "id": "declaration.entity.name.function_getActionLinkDiagnosticInfo_-1:0"
      },
      "accessModifier": {
        "type": "keyword.modifier.access",
        "text": "public",
        "textToLower": "public",
        "isAux": false,
        "range": {
          "start": {
            "line": -1,
            "character": 0
          },
          "end": {
            "line": -1,
            "character": 0
          },
          "isEmpty": true,
          "isSingleLine": true
        },
        "id": "keyword.modifier.access_public_-1:0"
      },
      "static": {
        "type": "keyword.modifier.static",
        "text": "static",
        "textToLower": "static",
        "isAux": false,
        "range": {
          "start": {
            "line": -1,
            "character": 0
          },
          "end": {
            "line": -1,
            "character": 0
          },
          "isEmpty": true,
          "isSingleLine": true
        },
        "id": "keyword.modifier.static_static_-1:0"
      },
      "signature": "public static ConnectApi.ActionLinkDiagnosticInfo getActionLinkDiagnosticInfo(String communityId, String actionLinkId)",
      "simplifiedSignature": "getActionLinkDiagnosticInfo(String,String)",
      "datatype": {
        "id": "ConnectApi.actionlinks.getactionlinkdiagnosticinfo.ConnectApi.ActionLinkDiagnosticInfo",
        "nodeType": "datatype",
        "name": "ConnectApi.ActionLinkDiagnosticInfo"
      },
      "description": "Get diagnostic information returned when an action link executes. Diagnostic information is given only for users who can access the action link.",
      "params": {
        "communityId": {
          "id": "ConnectApi.actionlinks.getactionlinkdiagnosticinfo.communityid",
          "type": "var",
          "name": "communityId",
          "startToken": {
            "type": "declaration.entity.name.variable",
            "text": "communityId",
            "textToLower": "communityid",
            "isAux": false,
            "range": {
              "start": {
                "line": -1,
                "character": 0
              },
              "end": {
                "line": -1,
                "character": 0
              },
              "isEmpty": true,
              "isSingleLine": true
            },
            "id": "declaration.entity.name.variable_communityId_-1:0"
          },
          "signature": "String communityId",
          "datatype": {
            "id": "ConnectApi.actionlinks.getactionlinkdiagnosticinfo.string",
            "nodeType": "datatype",
            "name": "String"
          }
        },
        "actionLinkId": {
          "id": "ConnectApi.actionlinks.getactionlinkdiagnosticinfo.actionlinkid",
          "type": "var",
          "name": "actionLinkId",
          "startToken": {
            "type": "declaration.entity.name.variable",
            "text": "actionLinkId",
            "textToLower": "actionlinkid",
            "isAux": false,
            "range": {
              "start": {
                "line": -1,
                "character": 0
              },
              "end": {
                "line": -1,
                "character": 0
              },
              "isEmpty": true,
              "isSingleLine": true
            },
            "id": "declaration.entity.name.variable_actionLinkId_-1:0"
          },
          "signature": "String actionLinkId",
          "datatype": {
            "id": "ConnectApi.actionlinks.getactionlinkdiagnosticinfo.string",
            "nodeType": "datatype",
            "name": "String"
          }
        }
      }
    },
    "getactionlinkgroup(string,string)": {
      "id": "ConnectApi.actionlinks.getactionlinkgroup",
      "nodeType": "method",
      "name": "getActionLinkGroup",
      "startToken": {
        "type": "declaration.entity.name.function",
        "text": "getActionLinkGroup",
        "textToLower": "getactionlinkgroup",
        "isAux": false,
        "range": {
          "start": {
            "line": -1,
            "character": 0
          },
          "end": {
            "line": -1,
            "character": 0
          },
          "isEmpty": true,
          "isSingleLine": true
        },
        "id": "declaration.entity.name.function_getActionLinkGroup_-1:0"
      },
      "accessModifier": {
        "type": "keyword.modifier.access",
        "text": "public",
        "textToLower": "public",
        "isAux": false,
        "range": {
          "start": {
            "line": -1,
            "character": 0
          },
          "end": {
            "line": -1,
            "character": 0
          },
          "isEmpty": true,
          "isSingleLine": true
        },
        "id": "keyword.modifier.access_public_-1:0"
      },
      "static": {
        "type": "keyword.modifier.static",
        "text": "static",
        "textToLower": "static",
        "isAux": false,
        "range": {
          "start": {
            "line": -1,
            "character": 0
          },
          "end": {
            "line": -1,
            "character": 0
          },
          "isEmpty": true,
          "isSingleLine": true
        },
        "id": "keyword.modifier.static_static_-1:0"
      },
      "signature": "public static ConnectApi.PlatformActionGroup getActionLinkGroup(String communityId, String actionLinkGroupId)",
      "simplifiedSignature": "getActionLinkGroup(String,String)",
      "datatype": {
        "id": "ConnectApi.actionlinks.getactionlinkgroup.ConnectApi.PlatformActionGroup",
        "nodeType": "datatype",
        "name": "ConnectApi.PlatformActionGroup"
      },
      "description": "Get information about an action link group including state for the context user.",
      "params": {
        "communityId": {
          "id": "ConnectApi.actionlinks.getactionlinkgroup.communityid",
          "type": "var",
          "name": "communityId",
          "startToken": {
            "type": "declaration.entity.name.variable",
            "text": "communityId",
            "textToLower": "communityid",
            "isAux": false,
            "range": {
              "start": {
                "line": -1,
                "character": 0
              },
              "end": {
                "line": -1,
                "character": 0
              },
              "isEmpty": true,
              "isSingleLine": true
            },
            "id": "declaration.entity.name.variable_communityId_-1:0"
          },
          "signature": "String communityId",
          "datatype": {
            "id": "ConnectApi.actionlinks.getactionlinkgroup.string",
            "nodeType": "datatype",
            "name": "String"
          }
        },
        "actionLinkGroupId": {
          "id": "ConnectApi.actionlinks.getactionlinkgroup.actionlinkgroupid",
          "type": "var",
          "name": "actionLinkGroupId",
          "startToken": {
            "type": "declaration.entity.name.variable",
            "text": "actionLinkGroupId",
            "textToLower": "actionlinkgroupid",
            "isAux": false,
            "range": {
              "start": {
                "line": -1,
                "character": 0
              },
              "end": {
                "line": -1,
                "character": 0
              },
              "isEmpty": true,
              "isSingleLine": true
            },
            "id": "declaration.entity.name.variable_actionLinkGroupId_-1:0"
          },
          "signature": "String actionLinkGroupId",
          "datatype": {
            "id": "ConnectApi.actionlinks.getactionlinkgroup.string",
            "nodeType": "datatype",
            "name": "String"
          }
        }
      }
    },
    "getactionlinkgroupdefinition(string,string)": {
      "id": "ConnectApi.actionlinks.getactionlinkgroupdefinition",
      "nodeType": "method",
      "name": "getActionLinkGroupDefinition",
      "startToken": {
        "type": "declaration.entity.name.function",
        "text": "getActionLinkGroupDefinition",
        "textToLower": "getactionlinkgroupdefinition",
        "isAux": false,
        "range": {
          "start": {
            "line": -1,
            "character": 0
          },
          "end": {
            "line": -1,
            "character": 0
          },
          "isEmpty": true,
          "isSingleLine": true
        },
        "id": "declaration.entity.name.function_getActionLinkGroupDefinition_-1:0"
      },
      "accessModifier": {
        "type": "keyword.modifier.access",
        "text": "public",
        "textToLower": "public",
        "isAux": false,
        "range": {
          "start": {
            "line": -1,
            "character": 0
          },
          "end": {
            "line": -1,
            "character": 0
          },
          "isEmpty": true,
          "isSingleLine": true
        },
        "id": "keyword.modifier.access_public_-1:0"
      },
      "static": {
        "type": "keyword.modifier.static",
        "text": "static",
        "textToLower": "static",
        "isAux": false,
        "range": {
          "start": {
            "line": -1,
            "character": 0
          },
          "end": {
            "line": -1,
            "character": 0
          },
          "isEmpty": true,
          "isSingleLine": true
        },
        "id": "keyword.modifier.static_static_-1:0"
      },
      "signature": "public static ConnectApi.ActionLinkGroupDefinition getActionLinkGroupDefinition(String communityId, String actionLinkGroupId)",
      "simplifiedSignature": "getActionLinkGroupDefinition(String,String)",
      "datatype": {
        "id": "ConnectApi.actionlinks.getactionlinkgroupdefinition.ConnectApi.ActionLinkGroupDefinition",
        "nodeType": "datatype",
        "name": "ConnectApi.ActionLinkGroupDefinition"
      },
      "description": "Get information about an action link group definition.",
      "params": {
        "communityId": {
          "id": "ConnectApi.actionlinks.getactionlinkgroupdefinition.communityid",
          "type": "var",
          "name": "communityId",
          "startToken": {
            "type": "declaration.entity.name.variable",
            "text": "communityId",
            "textToLower": "communityid",
            "isAux": false,
            "range": {
              "start": {
                "line": -1,
                "character": 0
              },
              "end": {
                "line": -1,
                "character": 0
              },
              "isEmpty": true,
              "isSingleLine": true
            },
            "id": "declaration.entity.name.variable_communityId_-1:0"
          },
          "signature": "String communityId",
          "datatype": {
            "id": "ConnectApi.actionlinks.getactionlinkgroupdefinition.string",
            "nodeType": "datatype",
            "name": "String"
          }
        },
        "actionLinkGroupId": {
          "id": "ConnectApi.actionlinks.getactionlinkgroupdefinition.actionlinkgroupid",
          "type": "var",
          "name": "actionLinkGroupId",
          "startToken": {
            "type": "declaration.entity.name.variable",
            "text": "actionLinkGroupId",
            "textToLower": "actionlinkgroupid",
            "isAux": false,
            "range": {
              "start": {
                "line": -1,
                "character": 0
              },
              "end": {
                "line": -1,
                "character": 0
              },
              "isEmpty": true,
              "isSingleLine": true
            },
            "id": "declaration.entity.name.variable_actionLinkGroupId_-1:0"
          },
          "signature": "String actionLinkGroupId",
          "datatype": {
            "id": "ConnectApi.actionlinks.getactionlinkgroupdefinition.string",
            "nodeType": "datatype",
            "name": "String"
          }
        }
      }
    }
  },
  "constructors": {},
  "extendsType": "",
  "implementTypes": [],
  "implements": {}
}