{
  "id": "Metadata.feedlayout",
  "nodeType": "class",
  "name": "FeedLayout",
  "namespace": "Metadata",
  "startToken": {
    "type": "declaration.entity.name.class",
    "text": "FeedLayout",
    "textToLower": "feedlayout",
    "isAux": false,
    "range": {
      "start": {
        "line": -1,
        "character": 0
      },
      "end": {
        "line": -1,
        "character": 0
      },
      "isEmpty": true,
      "isSingleLine": true
    },
    "id": "declaration.entity.name.class_FeedLayout_-1:0"
  },
  "accessModifier": {
    "type": "keyword.modifier.access",
    "text": "global",
    "textToLower": "global",
    "isAux": false,
    "range": {
      "start": {
        "line": -1,
        "character": 0
      },
      "end": {
        "line": -1,
        "character": 0
      },
      "isEmpty": true,
      "isSingleLine": true
    },
    "id": "keyword.modifier.access_global_-1:0"
  },
  "sharingModifier": {
    "type": "keyword.modifier.sharing",
    "text": "without sharing",
    "textToLower": "without sharing",
    "isAux": false,
    "range": {
      "start": {
        "line": -1,
        "character": 0
      },
      "end": {
        "line": -1,
        "character": 0
      },
      "isEmpty": true,
      "isSingleLine": true
    },
    "id": "keyword.modifier.sharing_without sharing_-1:0"
  },
  "description": "Represents the values that define the feed view of a feed-based page layout. Feed-based layouts are available on Account, Case, Contact, Lead, Opportunity, custom, and external objects. They include a feed view and a detail view.",
  "documentation": "https://developer.salesforce.com/docs/atlas.en-us.apexcode.meta/apexcode/apex_class_Metadata_FeedLayout.htm",
  "classes": {},
  "interfaces": {},
  "enums": {},
  "variables": {
    "autocollapsepublisher": {
      "id": "Metadata.feedlayout.autocollapsepublisher",
      "nodeType": "property",
      "name": "autocollapsePublisher",
      "startToken": {
        "type": "declaration.entity.name.property",
        "text": "autocollapsePublisher",
        "textToLower": "autocollapsepublisher",
        "isAux": false,
        "range": {
          "start": {
            "line": -1,
            "character": 0
          },
          "end": {
            "line": -1,
            "character": 0
          },
          "isEmpty": true,
          "isSingleLine": true
        },
        "id": "declaration.entity.name.property_autocollapsePublisher_-1:0"
      },
      "accessModifier": {
        "type": "keyword.modifier.access",
        "text": "public",
        "textToLower": "public",
        "isAux": false,
        "range": {
          "start": {
            "line": -1,
            "character": 0
          },
          "end": {
            "line": -1,
            "character": 0
          },
          "isEmpty": true,
          "isSingleLine": true
        },
        "id": "keyword.modifier.access_public_-1:0"
      },
      "signature": "public Boolean autocollapsePublisher {get; set;}",
      "simplifiedSignature": "Boolean autocollapsePublisher { get; set; }",
      "datatype": {
        "id": "Metadata.feedlayout.autocollapsepublisher.boolean",
        "nodeType": "datatype",
        "name": "Boolean"
      },
      "description": "Specifies whether the publisher is collapsed when the page loads (true) or not (false).",
      "getter": {
        "id": "Metadata.feedlayout.autocollapsepublisher.get",
        "nodeType": "getter",
        "name": "get",
        "startToken": {
          "type": "keyword.declaration.property.getter",
          "text": "get",
          "textToLower": "get",
          "isAux": false,
          "range": {
            "start": {
              "line": -1,
              "character": 0
            },
            "end": {
              "line": -1,
              "character": 0
            },
            "isEmpty": true,
            "isSingleLine": true
          },
          "id": "keyword.declaration.property.getter_get_-1:0"
        }
      },
      "setter": {
        "id": "Metadata.feedlayout.autocollapsepublisher.set",
        "nodeType": "setter",
        "name": "set",
        "startToken": {
          "type": "keyword.declaration.property.setter",
          "text": "set",
          "textToLower": "set",
          "isAux": false,
          "range": {
            "start": {
              "line": -1,
              "character": 0
            },
            "end": {
              "line": -1,
              "character": 0
            },
            "isEmpty": true,
            "isSingleLine": true
          },
          "id": "keyword.declaration.property.setter_set_-1:0"
        }
      }
    },
    "compactfeed": {
      "id": "Metadata.feedlayout.compactfeed",
      "nodeType": "property",
      "name": "compactFeed",
      "startToken": {
        "type": "declaration.entity.name.property",
        "text": "compactFeed",
        "textToLower": "compactfeed",
        "isAux": false,
        "range": {
          "start": {
            "line": -1,
            "character": 0
          },
          "end": {
            "line": -1,
            "character": 0
          },
          "isEmpty": true,
          "isSingleLine": true
        },
        "id": "declaration.entity.name.property_compactFeed_-1:0"
      },
      "accessModifier": {
        "type": "keyword.modifier.access",
        "text": "public",
        "textToLower": "public",
        "isAux": false,
        "range": {
          "start": {
            "line": -1,
            "character": 0
          },
          "end": {
            "line": -1,
            "character": 0
          },
          "isEmpty": true,
          "isSingleLine": true
        },
        "id": "keyword.modifier.access_public_-1:0"
      },
      "signature": "public Boolean compactFeed {get; set;}",
      "simplifiedSignature": "Boolean compactFeed { get; set; }",
      "datatype": {
        "id": "Metadata.feedlayout.compactfeed.boolean",
        "nodeType": "datatype",
        "name": "Boolean"
      },
      "description": "Specifies whether the feed-based page layout uses a compact feed (true) or not (false). If set to true, feed items on the page are collapsed by default, and the feed view has an updated design.",
      "getter": {
        "id": "Metadata.feedlayout.compactfeed.get",
        "nodeType": "getter",
        "name": "get",
        "startToken": {
          "type": "keyword.declaration.property.getter",
          "text": "get",
          "textToLower": "get",
          "isAux": false,
          "range": {
            "start": {
              "line": -1,
              "character": 0
            },
            "end": {
              "line": -1,
              "character": 0
            },
            "isEmpty": true,
            "isSingleLine": true
          },
          "id": "keyword.declaration.property.getter_get_-1:0"
        }
      },
      "setter": {
        "id": "Metadata.feedlayout.compactfeed.set",
        "nodeType": "setter",
        "name": "set",
        "startToken": {
          "type": "keyword.declaration.property.setter",
          "text": "set",
          "textToLower": "set",
          "isAux": false,
          "range": {
            "start": {
              "line": -1,
              "character": 0
            },
            "end": {
              "line": -1,
              "character": 0
            },
            "isEmpty": true,
            "isSingleLine": true
          },
          "id": "keyword.declaration.property.setter_set_-1:0"
        }
      }
    },
    "feedfilterposition": {
      "id": "Metadata.feedlayout.feedfilterposition",
      "nodeType": "property",
      "name": "feedFilterPosition",
      "startToken": {
        "type": "declaration.entity.name.property",
        "text": "feedFilterPosition",
        "textToLower": "feedfilterposition",
        "isAux": false,
        "range": {
          "start": {
            "line": -1,
            "character": 0
          },
          "end": {
            "line": -1,
            "character": 0
          },
          "isEmpty": true,
          "isSingleLine": true
        },
        "id": "declaration.entity.name.property_feedFilterPosition_-1:0"
      },
      "accessModifier": {
        "type": "keyword.modifier.access",
        "text": "public",
        "textToLower": "public",
        "isAux": false,
        "range": {
          "start": {
            "line": -1,
            "character": 0
          },
          "end": {
            "line": -1,
            "character": 0
          },
          "isEmpty": true,
          "isSingleLine": true
        },
        "id": "keyword.modifier.access_public_-1:0"
      },
      "signature": "public Metadata.FeedLayoutFilterPosition feedFilterPosition {get; set;}",
      "simplifiedSignature": "Metadata.FeedLayoutFilterPosition feedFilterPosition { get; set; }",
      "datatype": {
        "id": "Metadata.feedlayout.feedfilterposition.metadata.feedlayoutfilterposition",
        "nodeType": "datatype",
        "name": "Metadata.FeedLayoutFilterPosition"
      },
      "description": "Indicates where the feed filters list is included in the layout.",
      "getter": {
        "id": "Metadata.feedlayout.feedfilterposition.get",
        "nodeType": "getter",
        "name": "get",
        "startToken": {
          "type": "keyword.declaration.property.getter",
          "text": "get",
          "textToLower": "get",
          "isAux": false,
          "range": {
            "start": {
              "line": -1,
              "character": 0
            },
            "end": {
              "line": -1,
              "character": 0
            },
            "isEmpty": true,
            "isSingleLine": true
          },
          "id": "keyword.declaration.property.getter_get_-1:0"
        }
      },
      "setter": {
        "id": "Metadata.feedlayout.feedfilterposition.set",
        "nodeType": "setter",
        "name": "set",
        "startToken": {
          "type": "keyword.declaration.property.setter",
          "text": "set",
          "textToLower": "set",
          "isAux": false,
          "range": {
            "start": {
              "line": -1,
              "character": 0
            },
            "end": {
              "line": -1,
              "character": 0
            },
            "isEmpty": true,
            "isSingleLine": true
          },
          "id": "keyword.declaration.property.setter_set_-1:0"
        }
      }
    },
    "feedfilters": {
      "id": "Metadata.feedlayout.feedfilters",
      "nodeType": "property",
      "name": "feedFilters",
      "startToken": {
        "type": "declaration.entity.name.property",
        "text": "feedFilters",
        "textToLower": "feedfilters",
        "isAux": false,
        "range": {
          "start": {
            "line": -1,
            "character": 0
          },
          "end": {
            "line": -1,
            "character": 0
          },
          "isEmpty": true,
          "isSingleLine": true
        },
        "id": "declaration.entity.name.property_feedFilters_-1:0"
      },
      "accessModifier": {
        "type": "keyword.modifier.access",
        "text": "public",
        "textToLower": "public",
        "isAux": false,
        "range": {
          "start": {
            "line": -1,
            "character": 0
          },
          "end": {
            "line": -1,
            "character": 0
          },
          "isEmpty": true,
          "isSingleLine": true
        },
        "id": "keyword.modifier.access_public_-1:0"
      },
      "signature": "public List<Metadata.FeedLayoutFilter> feedFilters {get; set;}",
      "simplifiedSignature": "List<Metadata.FeedLayoutFilter> feedFilters { get; set; }",
      "datatype": {
        "id": "Metadata.feedlayout.feedfilters.list<metadata.feedlayoutfilter>",
        "nodeType": "datatype",
        "name": "List<Metadata.FeedLayoutFilter>"
      },
      "description": "The individual filters displayed in the feed filters list.",
      "getter": {
        "id": "Metadata.feedlayout.feedfilters.get",
        "nodeType": "getter",
        "name": "get",
        "startToken": {
          "type": "keyword.declaration.property.getter",
          "text": "get",
          "textToLower": "get",
          "isAux": false,
          "range": {
            "start": {
              "line": -1,
              "character": 0
            },
            "end": {
              "line": -1,
              "character": 0
            },
            "isEmpty": true,
            "isSingleLine": true
          },
          "id": "keyword.declaration.property.getter_get_-1:0"
        }
      },
      "setter": {
        "id": "Metadata.feedlayout.feedfilters.set",
        "nodeType": "setter",
        "name": "set",
        "startToken": {
          "type": "keyword.declaration.property.setter",
          "text": "set",
          "textToLower": "set",
          "isAux": false,
          "range": {
            "start": {
              "line": -1,
              "character": 0
            },
            "end": {
              "line": -1,
              "character": 0
            },
            "isEmpty": true,
            "isSingleLine": true
          },
          "id": "keyword.declaration.property.setter_set_-1:0"
        }
      }
    },
    "fullwidthfeed": {
      "id": "Metadata.feedlayout.fullwidthfeed",
      "nodeType": "property",
      "name": "fullWidthFeed",
      "startToken": {
        "type": "declaration.entity.name.property",
        "text": "fullWidthFeed",
        "textToLower": "fullwidthfeed",
        "isAux": false,
        "range": {
          "start": {
            "line": -1,
            "character": 0
          },
          "end": {
            "line": -1,
            "character": 0
          },
          "isEmpty": true,
          "isSingleLine": true
        },
        "id": "declaration.entity.name.property_fullWidthFeed_-1:0"
      },
      "accessModifier": {
        "type": "keyword.modifier.access",
        "text": "public",
        "textToLower": "public",
        "isAux": false,
        "range": {
          "start": {
            "line": -1,
            "character": 0
          },
          "end": {
            "line": -1,
            "character": 0
          },
          "isEmpty": true,
          "isSingleLine": true
        },
        "id": "keyword.modifier.access_public_-1:0"
      },
      "signature": "public Boolean fullWidthFeed {get; set;}",
      "simplifiedSignature": "Boolean fullWidthFeed { get; set; }",
      "datatype": {
        "id": "Metadata.feedlayout.fullwidthfeed.boolean",
        "nodeType": "datatype",
        "name": "Boolean"
      },
      "description": "Specifies whether the feed expands horizontally to take up all available space on the page (true) or not (false).",
      "getter": {
        "id": "Metadata.feedlayout.fullwidthfeed.get",
        "nodeType": "getter",
        "name": "get",
        "startToken": {
          "type": "keyword.declaration.property.getter",
          "text": "get",
          "textToLower": "get",
          "isAux": false,
          "range": {
            "start": {
              "line": -1,
              "character": 0
            },
            "end": {
              "line": -1,
              "character": 0
            },
            "isEmpty": true,
            "isSingleLine": true
          },
          "id": "keyword.declaration.property.getter_get_-1:0"
        }
      },
      "setter": {
        "id": "Metadata.feedlayout.fullwidthfeed.set",
        "nodeType": "setter",
        "name": "set",
        "startToken": {
          "type": "keyword.declaration.property.setter",
          "text": "set",
          "textToLower": "set",
          "isAux": false,
          "range": {
            "start": {
              "line": -1,
              "character": 0
            },
            "end": {
              "line": -1,
              "character": 0
            },
            "isEmpty": true,
            "isSingleLine": true
          },
          "id": "keyword.declaration.property.setter_set_-1:0"
        }
      }
    },
    "hidesidebar": {
      "id": "Metadata.feedlayout.hidesidebar",
      "nodeType": "property",
      "name": "hideSidebar",
      "startToken": {
        "type": "declaration.entity.name.property",
        "text": "hideSidebar",
        "textToLower": "hidesidebar",
        "isAux": false,
        "range": {
          "start": {
            "line": -1,
            "character": 0
          },
          "end": {
            "line": -1,
            "character": 0
          },
          "isEmpty": true,
          "isSingleLine": true
        },
        "id": "declaration.entity.name.property_hideSidebar_-1:0"
      },
      "accessModifier": {
        "type": "keyword.modifier.access",
        "text": "public",
        "textToLower": "public",
        "isAux": false,
        "range": {
          "start": {
            "line": -1,
            "character": 0
          },
          "end": {
            "line": -1,
            "character": 0
          },
          "isEmpty": true,
          "isSingleLine": true
        },
        "id": "keyword.modifier.access_public_-1:0"
      },
      "signature": "public Boolean hideSidebar {get; set;}",
      "simplifiedSignature": "Boolean hideSidebar { get; set; }",
      "datatype": {
        "id": "Metadata.feedlayout.hidesidebar.boolean",
        "nodeType": "datatype",
        "name": "Boolean"
      },
      "description": "Specifies whether the sidebar is hidden (true) or not (false).",
      "getter": {
        "id": "Metadata.feedlayout.hidesidebar.get",
        "nodeType": "getter",
        "name": "get",
        "startToken": {
          "type": "keyword.declaration.property.getter",
          "text": "get",
          "textToLower": "get",
          "isAux": false,
          "range": {
            "start": {
              "line": -1,
              "character": 0
            },
            "end": {
              "line": -1,
              "character": 0
            },
            "isEmpty": true,
            "isSingleLine": true
          },
          "id": "keyword.declaration.property.getter_get_-1:0"
        }
      },
      "setter": {
        "id": "Metadata.feedlayout.hidesidebar.set",
        "nodeType": "setter",
        "name": "set",
        "startToken": {
          "type": "keyword.declaration.property.setter",
          "text": "set",
          "textToLower": "set",
          "isAux": false,
          "range": {
            "start": {
              "line": -1,
              "character": 0
            },
            "end": {
              "line": -1,
              "character": 0
            },
            "isEmpty": true,
            "isSingleLine": true
          },
          "id": "keyword.declaration.property.setter_set_-1:0"
        }
      }
    },
    "highlightexternalfeeditems": {
      "id": "Metadata.feedlayout.highlightexternalfeeditems",
      "nodeType": "property",
      "name": "highlightExternalFeedItems",
      "startToken": {
        "type": "declaration.entity.name.property",
        "text": "highlightExternalFeedItems",
        "textToLower": "highlightexternalfeeditems",
        "isAux": false,
        "range": {
          "start": {
            "line": -1,
            "character": 0
          },
          "end": {
            "line": -1,
            "character": 0
          },
          "isEmpty": true,
          "isSingleLine": true
        },
        "id": "declaration.entity.name.property_highlightExternalFeedItems_-1:0"
      },
      "accessModifier": {
        "type": "keyword.modifier.access",
        "text": "public",
        "textToLower": "public",
        "isAux": false,
        "range": {
          "start": {
            "line": -1,
            "character": 0
          },
          "end": {
            "line": -1,
            "character": 0
          },
          "isEmpty": true,
          "isSingleLine": true
        },
        "id": "keyword.modifier.access_public_-1:0"
      },
      "signature": "public Boolean highlightExternalFeedItems {get; set;}",
      "simplifiedSignature": "Boolean highlightExternalFeedItems { get; set; }",
      "datatype": {
        "id": "Metadata.feedlayout.highlightexternalfeeditems.boolean",
        "nodeType": "datatype",
        "name": "Boolean"
      },
      "description": "Controls whether to highlight external feed items (true) or not (false).",
      "getter": {
        "id": "Metadata.feedlayout.highlightexternalfeeditems.get",
        "nodeType": "getter",
        "name": "get",
        "startToken": {
          "type": "keyword.declaration.property.getter",
          "text": "get",
          "textToLower": "get",
          "isAux": false,
          "range": {
            "start": {
              "line": -1,
              "character": 0
            },
            "end": {
              "line": -1,
              "character": 0
            },
            "isEmpty": true,
            "isSingleLine": true
          },
          "id": "keyword.declaration.property.getter_get_-1:0"
        }
      },
      "setter": {
        "id": "Metadata.feedlayout.highlightexternalfeeditems.set",
        "nodeType": "setter",
        "name": "set",
        "startToken": {
          "type": "keyword.declaration.property.setter",
          "text": "set",
          "textToLower": "set",
          "isAux": false,
          "range": {
            "start": {
              "line": -1,
              "character": 0
            },
            "end": {
              "line": -1,
              "character": 0
            },
            "isEmpty": true,
            "isSingleLine": true
          },
          "id": "keyword.declaration.property.setter_set_-1:0"
        }
      }
    },
    "leftcomponents": {
      "id": "Metadata.feedlayout.leftcomponents",
      "nodeType": "property",
      "name": "leftComponents",
      "startToken": {
        "type": "declaration.entity.name.property",
        "text": "leftComponents",
        "textToLower": "leftcomponents",
        "isAux": false,
        "range": {
          "start": {
            "line": -1,
            "character": 0
          },
          "end": {
            "line": -1,
            "character": 0
          },
          "isEmpty": true,
          "isSingleLine": true
        },
        "id": "declaration.entity.name.property_leftComponents_-1:0"
      },
      "accessModifier": {
        "type": "keyword.modifier.access",
        "text": "public",
        "textToLower": "public",
        "isAux": false,
        "range": {
          "start": {
            "line": -1,
            "character": 0
          },
          "end": {
            "line": -1,
            "character": 0
          },
          "isEmpty": true,
          "isSingleLine": true
        },
        "id": "keyword.modifier.access_public_-1:0"
      },
      "signature": "public List<Metadata.FeedLayoutComponent> leftComponents {get; set;}",
      "simplifiedSignature": "List<Metadata.FeedLayoutComponent> leftComponents { get; set; }",
      "datatype": {
        "id": "Metadata.feedlayout.leftcomponents.list<metadata.feedlayoutcomponent>",
        "nodeType": "datatype",
        "name": "List<Metadata.FeedLayoutComponent>"
      },
      "description": "The individual components displayed in the left column of the feed view.",
      "getter": {
        "id": "Metadata.feedlayout.leftcomponents.get",
        "nodeType": "getter",
        "name": "get",
        "startToken": {
          "type": "keyword.declaration.property.getter",
          "text": "get",
          "textToLower": "get",
          "isAux": false,
          "range": {
            "start": {
              "line": -1,
              "character": 0
            },
            "end": {
              "line": -1,
              "character": 0
            },
            "isEmpty": true,
            "isSingleLine": true
          },
          "id": "keyword.declaration.property.getter_get_-1:0"
        }
      },
      "setter": {
        "id": "Metadata.feedlayout.leftcomponents.set",
        "nodeType": "setter",
        "name": "set",
        "startToken": {
          "type": "keyword.declaration.property.setter",
          "text": "set",
          "textToLower": "set",
          "isAux": false,
          "range": {
            "start": {
              "line": -1,
              "character": 0
            },
            "end": {
              "line": -1,
              "character": 0
            },
            "isEmpty": true,
            "isSingleLine": true
          },
          "id": "keyword.declaration.property.setter_set_-1:0"
        }
      }
    },
    "rightcomponents": {
      "id": "Metadata.feedlayout.rightcomponents",
      "nodeType": "property",
      "name": "rightComponents",
      "startToken": {
        "type": "declaration.entity.name.property",
        "text": "rightComponents",
        "textToLower": "rightcomponents",
        "isAux": false,
        "range": {
          "start": {
            "line": -1,
            "character": 0
          },
          "end": {
            "line": -1,
            "character": 0
          },
          "isEmpty": true,
          "isSingleLine": true
        },
        "id": "declaration.entity.name.property_rightComponents_-1:0"
      },
      "accessModifier": {
        "type": "keyword.modifier.access",
        "text": "public",
        "textToLower": "public",
        "isAux": false,
        "range": {
          "start": {
            "line": -1,
            "character": 0
          },
          "end": {
            "line": -1,
            "character": 0
          },
          "isEmpty": true,
          "isSingleLine": true
        },
        "id": "keyword.modifier.access_public_-1:0"
      },
      "signature": "public List<Metadata.FeedLayoutComponent> rightComponents {get; set;}",
      "simplifiedSignature": "List<Metadata.FeedLayoutComponent> rightComponents { get; set; }",
      "datatype": {
        "id": "Metadata.feedlayout.rightcomponents.list<metadata.feedlayoutcomponent>",
        "nodeType": "datatype",
        "name": "List<Metadata.FeedLayoutComponent>"
      },
      "description": "Lists the individual components displayed in the right column of the feed view.",
      "getter": {
        "id": "Metadata.feedlayout.rightcomponents.get",
        "nodeType": "getter",
        "name": "get",
        "startToken": {
          "type": "keyword.declaration.property.getter",
          "text": "get",
          "textToLower": "get",
          "isAux": false,
          "range": {
            "start": {
              "line": -1,
              "character": 0
            },
            "end": {
              "line": -1,
              "character": 0
            },
            "isEmpty": true,
            "isSingleLine": true
          },
          "id": "keyword.declaration.property.getter_get_-1:0"
        }
      },
      "setter": {
        "id": "Metadata.feedlayout.rightcomponents.set",
        "nodeType": "setter",
        "name": "set",
        "startToken": {
          "type": "keyword.declaration.property.setter",
          "text": "set",
          "textToLower": "set",
          "isAux": false,
          "range": {
            "start": {
              "line": -1,
              "character": 0
            },
            "end": {
              "line": -1,
              "character": 0
            },
            "isEmpty": true,
            "isSingleLine": true
          },
          "id": "keyword.declaration.property.setter_set_-1:0"
        }
      }
    },
    "useinlinefiltersinconsole": {
      "id": "Metadata.feedlayout.useinlinefiltersinconsole",
      "nodeType": "property",
      "name": "useInlineFiltersInConsole",
      "startToken": {
        "type": "declaration.entity.name.property",
        "text": "useInlineFiltersInConsole",
        "textToLower": "useinlinefiltersinconsole",
        "isAux": false,
        "range": {
          "start": {
            "line": -1,
            "character": 0
          },
          "end": {
            "line": -1,
            "character": 0
          },
          "isEmpty": true,
          "isSingleLine": true
        },
        "id": "declaration.entity.name.property_useInlineFiltersInConsole_-1:0"
      },
      "accessModifier": {
        "type": "keyword.modifier.access",
        "text": "public",
        "textToLower": "public",
        "isAux": false,
        "range": {
          "start": {
            "line": -1,
            "character": 0
          },
          "end": {
            "line": -1,
            "character": 0
          },
          "isEmpty": true,
          "isSingleLine": true
        },
        "id": "keyword.modifier.access_public_-1:0"
      },
      "signature": "public Boolean useInlineFiltersInConsole {get; set;}",
      "simplifiedSignature": "Boolean useInlineFiltersInConsole { get; set; }",
      "datatype": {
        "id": "Metadata.feedlayout.useinlinefiltersinconsole.boolean",
        "nodeType": "datatype",
        "name": "Boolean"
      },
      "description": "Indicates whether to use inline filters in the Salesforce console.",
      "getter": {
        "id": "Metadata.feedlayout.useinlinefiltersinconsole.get",
        "nodeType": "getter",
        "name": "get",
        "startToken": {
          "type": "keyword.declaration.property.getter",
          "text": "get",
          "textToLower": "get",
          "isAux": false,
          "range": {
            "start": {
              "line": -1,
              "character": 0
            },
            "end": {
              "line": -1,
              "character": 0
            },
            "isEmpty": true,
            "isSingleLine": true
          },
          "id": "keyword.declaration.property.getter_get_-1:0"
        }
      },
      "setter": {
        "id": "Metadata.feedlayout.useinlinefiltersinconsole.set",
        "nodeType": "setter",
        "name": "set",
        "startToken": {
          "type": "keyword.declaration.property.setter",
          "text": "set",
          "textToLower": "set",
          "isAux": false,
          "range": {
            "start": {
              "line": -1,
              "character": 0
            },
            "end": {
              "line": -1,
              "character": 0
            },
            "isEmpty": true,
            "isSingleLine": true
          },
          "id": "keyword.declaration.property.setter_set_-1:0"
        }
      }
    }
  },
  "methods": {
    "clone()": {
      "id": "Metadata.feedlayout.clone",
      "nodeType": "method",
      "name": "clone",
      "startToken": {
        "type": "declaration.entity.name.function",
        "text": "clone",
        "textToLower": "clone",
        "isAux": false,
        "range": {
          "start": {
            "line": -1,
            "character": 0
          },
          "end": {
            "line": -1,
            "character": 0
          },
          "isEmpty": true,
          "isSingleLine": true
        },
        "id": "declaration.entity.name.function_clone_-1:0"
      },
      "accessModifier": {
        "type": "keyword.modifier.access",
        "text": "public",
        "textToLower": "public",
        "isAux": false,
        "range": {
          "start": {
            "line": -1,
            "character": 0
          },
          "end": {
            "line": -1,
            "character": 0
          },
          "isEmpty": true,
          "isSingleLine": true
        },
        "id": "keyword.modifier.access_public_-1:0"
      },
      "signature": "public Object clone()",
      "simplifiedSignature": "clone()",
      "datatype": {
        "id": "Metadata.feedlayout.clone.Object",
        "nodeType": "datatype",
        "name": "Object"
      },
      "description": "Makes a duplicate copy of the Metadata.FeedLayout.",
      "params": {}
    }
  },
  "constructors": {},
  "extendsType": "",
  "implementTypes": [],
  "implements": {}
}